datasette_auth_osm/__init__.py
datasette_auth_osm-0.3.dist-info/licenses/LICENSE
datasette_auth_osm-0.3.dist-info/METADATA
datasette_auth_osm-0.3.dist-info/WHEEL
datasette_auth_osm-0.3.dist-info/entry_points.txt
datasette_auth_osm-0.3.dist-info/top_level.txt
datasette_auth_osm-0.3.dist-info/RECORD
