Metadata-Version: 2.4
Name: datasette-auth-osm
Version: 0.3
Summary: Datasette plugin that authenticates users against Openstreetmap
Home-page: https://github.com/mfa/datasette-auth-osm
Author: Andreas Madsack
License: Apache License, Version 2.0
Project-URL: Issues, https://github.com/mfa/datasette-auth-osm/issues
Project-URL: CI, https://github.com/mfa/datasette-auth-osm/actions
Classifier: Framework :: Datasette
Classifier: License :: OSI Approved :: Apache Software License
Requires-Python: >=3.7
License-File: LICENSE
Requires-Dist: datasette
Requires-Dist: python-baseconv
Provides-Extra: test
Requires-Dist: pytest; extra == "test"
Requires-Dist: pytest-asyncio; extra == "test"
Requires-Dist: pytest-httpx; extra == "test"
Dynamic: author
Dynamic: classifier
Dynamic: description
Dynamic: description-content-type
Dynamic: home-page
Dynamic: license
Dynamic: license-file
Dynamic: project-url
Dynamic: provides-extra
Dynamic: requires-dist
Dynamic: requires-python
Dynamic: summary
